botoplier/__init__.py
botoplier/__main__.py
botoplier/_shapes.py
botoplier/_version.py
botoplier/py.typed
botoplier/sessions.py
botoplier/types.py
botoplier/asyncio/__init__.py
botoplier/asyncio/sessions.py
botoplier/asyncio/smart_query.py
botoplier/config/__init__.py
botoplier/sync/__init__.py
botoplier/sync/sessions.py
botoplier/sync/smart_query.py
botoplier/util/__init__.py
botoplier/util/dictutils.py
botoplier/util/json.py
botoplier/util/listutils.py
botoplier/util/timeutils.py
botoplier/util/treeutils.py
botoplier-0.0.1rc2.dist-info/METADATA
botoplier-0.0.1rc2.dist-info/WHEEL
botoplier-0.0.1rc2.dist-info/entry_points.txt
botoplier-0.0.1rc2.dist-info/licenses/LICENSE
botoplier-0.0.1rc2.dist-info/RECORD
