Metadata-Version: 2.3
Name: botoplier
Version: 0.0.1rc2
Summary: A powerful yet simple way to use AWS APIs, built on boto3
Project-URL: Repository, https://github.com/ManoManoTech/botoplier
Author-email: Elie Bleton <elie.bleton@manomano.com>
License: Copyright (c) 2024 "ManoMano" Colibri SAS
License-File: LICENSE
Classifier: Development Status :: 3 - Alpha
Classifier: Intended Audience :: Developers
Classifier: License :: OSI Approved :: ISC License (ISCL)
Classifier: Operating System :: OS Independent
Classifier: Programming Language :: Python :: 3 :: Only
Classifier: Programming Language :: Python :: 3.9
Classifier: Programming Language :: Python :: 3.10
Classifier: Programming Language :: Python :: 3.11
Classifier: Programming Language :: Python :: 3.12
Classifier: Topic :: Software Development :: Libraries :: Python Modules
Classifier: Topic :: Utilities
Classifier: Typing :: Typed
Requires-Python: >=3.9
Requires-Dist: boto3>=1.34.139
Requires-Dist: jq>=1.7
Requires-Dist: treelib>=1.7
